__init__.py
pychemelt/__init__.py
pychemelt/main.py
pychemelt/monomer.py
pychemelt/experimental/dev_code.py
pychemelt/experimental/dev_code_main.py
pychemelt/utils/__init__.py
pychemelt/utils/constants.py
pychemelt/utils/files.py
pychemelt/utils/fitting.py
pychemelt/utils/fractions.py
pychemelt/utils/math.py
pychemelt/utils/palette.py
pychemelt/utils/plotting.py
pychemelt/utils/processing.py
pychemelt/utils/rates.py
pychemelt/utils/signals.py
pychemelt/utils/svd.py
pychemelt-0.1.12.dist-info/METADATA
pychemelt-0.1.12.dist-info/WHEEL
pychemelt-0.1.12.dist-info/top_level.txt
pychemelt-0.1.12.dist-info/RECORD
